Verilog/2019_.v
/*
Name : Harpinder Jot Singh
ID	 : 2017A7PS0057P
*/
`timescale 1ms/1ns
module MUX_2x1(
	output E,
	input C,
	input D,
	input F
);

	assign E = F ? D : C;

endmodule

module MUX_8x1(
	output O,
	input [7:0] E,
	input [2:0] Q
);

	assign O = Q[2] ? 
					(Q[1] ? 
						( (Q[0] ? (E[7]) : (E[6]) ) ) 
					:   ( (Q[0] ? (E[5]) : (E[4]) )) ) 
				  : (Q[1] ? 
						( (Q[0] ? (E[3]) : (E[2]) )) 
					:   ( (Q[0] ? (E[1]) : (E[0]) )));

endmodule

module MUX_ARRAY(
	output [7:0] E,
	input [7:0] C,
	input [7:0] D,
	input [7:0] F
);
	
	//wire ground = 1'b0;
	
	genvar i;
	
	generate for(i = 0; i < 8; i = i+1) begin :muxarr
		
		MUX_2x1 mux( E[i], D[i], C[i], F[i] );
		
	end
	endgenerate

endmodule

module COUNTER_3BIT(
	output [2:0] Q,
	input CLEAR,
	input CLK
);

	reg [2:0] Q;
	
	initial 
		Q = 3'b0;
	
	always @(posedge CLK) begin
		Q <= Q + 1;
	end
	
	always @(CLEAR)
		if(CLEAR) 
			Q <= 3'b0;
	
	

endmodule



module DECODER(
	
	output [7:0] B,
	input EN,
	input [2:0] A
	
);
	reg [7:0] B;
	always @(A) begin
		if(EN) begin
			case(A) 
				
				3'd0 : B = 8'b0000_0001;
				3'd1 : B = 8'b0000_0010;
				3'd2 : B = 8'b0000_0100;
				3'd3 : B = 8'b0000_1000;
				
				3'd4 : B = 8'b0001_0000;
				3'd5 : B = 8'b0010_0000;
				3'd6 : B = 8'b0100_0000;
				3'd7 : B = 8'b1000_0000;
			
			endcase
		end
	end


endmodule




module MEMORY(
	
	output [7:0] G,
	input [2:0] A
	
);

	reg [7:0] memory[0:7];
	reg [7:0] G;
	
	always @(A) begin
		
		case(A) 
			
			3'd0 : G = memory[0];
			3'd1 : G = memory[1];
			3'd2 : G = memory[2];
			3'd3 : G = memory[3];
			
			3'd4 : G = memory[4];
			3'd5 : G = memory[5];
			3'd6 : G = memory[6];
			3'd7 : G = memory[7];
		
		endcase
	end
		
	
	integer i;
	
	initial begin
		
		memory[0] = 8'h01;
		memory[1] = 8'h03;
		memory[2] = 8'h07;
		memory[3] = 8'h0F;
		
		memory[4] = 8'h1F;
		memory[5] = 8'h3F;
		memory[6] = 8'h7F;
		memory[7] = 8'hFF;
		
	end

endmodule



module TOP_MODULE(

	output O,
	input CLK,
	input CLEAR,
	input [2:0] S
);
	wire [2:0] Q;
	
	COUNTER_3BIT cnt(Q, CLEAR, CLK);
	
	wire [7:0] B;
	
	DECODER dec(B, 1'b1, Q);
	
	wire [7:0] G;
	MEMORY mem(G, S);
	
	wire [7:0] E;
	wire [7:0] GROUND = 8'b0;
	MUX_ARRAY arr(E, B,GROUND, G);
	
	MUX_8x1 mux(O, E, Q);
	
	

endmodule


module TB_TOPMODULE();

	initial begin
		$dumpfile("file.vcd");
		$dumpvars;
	end
	
	
	wire O;
	reg CLK;
	reg CLEAR;
	reg [2:0] S;
	
	TOP_MODULE mod(O, CLK, CLEAR, S);
	
	always	
		#0.5 CLK = ~CLK;
	
	initial begin
			CLK = 1'b0;
			S = 3'b0;
			CLEAR = 1'b1;
		#1	CLEAR = 1'b0;
		#100 $finish;
	end
	
	always
		#8	S = S+1;
	
	initial
		$monitor($time,"  , CLK = %b, S = %b, CLEAR = %b, O = %b", CLK, S, CLEAR, O);
endmodule

Verilog/file.vcd
$date
	Sun Nov 28 01:18:56 2021
$end
$version
	Icarus Verilog
$end
$timescale
	1ns
$end
$scope module TB_TOPMODULE $end
$var wire 1 ! O $end
$var reg 1 " CLEAR $end
$var reg 1 # CLK $end
$var reg 3 $ S [2:0] $end
$scope module mod $end
$var wire 1 " CLEAR $end
$var wire 1 # CLK $end
$var wire 8 % GROUND [7:0] $end
$var wire 3 & S [2:0] $end
$var wire 3 ' Q [2:0] $end
$var wire 1 ! O $end
$var wire 8 ( G [7:0] $end
$var wire 8 ) E [7:0] $end
$var wire 8 * B [7:0] $end
$scope module arr $end
$var wire 8 + D [7:0] $end
$var wire 8 , F [7:0] $end
$var wire 8 - E [7:0] $end
$var wire 8 . C [7:0] $end
$scope begin muxarr[0] $end
$scope module mux $end
$var wire 1 / C $end
$var wire 1 0 D $end
$var wire 1 1 F $end
$var wire 1 2 E $end
$upscope $end
$upscope $end
$scope begin muxarr[1] $end
$scope module mux $end
$var wire 1 3 C $end
$var wire 1 4 D $end
$var wire 1 5 F $end
$var wire 1 6 E $end
$upscope $end
$upscope $end
$scope begin muxarr[2] $end
$scope module mux $end
$var wire 1 7 C $end
$var wire 1 8 D $end
$var wire 1 9 F $end
$var wire 1 : E $end
$upscope $end
$upscope $end
$scope begin muxarr[3] $end
$scope module mux $end
$var wire 1 ; C $end
$var wire 1 < D $end
$var wire 1 = F $end
$var wire 1 > E $end
$upscope $end
$upscope $end
$scope begin muxarr[4] $end
$scope module mux $end
$var wire 1 ? C $end
$var wire 1 @ D $end
$var wire 1 A F $end
$var wire 1 B E $end
$upscope $end
$upscope $end
$scope begin muxarr[5] $end
$scope module mux $end
$var wire 1 C C $end
$var wire 1 D D $end
$var wire 1 E F $end
$var wire 1 F E $end
$upscope $end
$upscope $end
$scope begin muxarr[6] $end
$scope module mux $end
$var wire 1 G C $end
$var wire 1 H D $end
$var wire 1 I F $end
$var wire 1 J E $end
$upscope $end
$upscope $end
$scope begin muxarr[7] $end
$scope module mux $end
$var wire 1 K C $end
$var wire 1 L D $end
$var wire 1 M F $end
$var wire 1 N E $end
$upscope $end
$upscope $end
$upscope $end
$scope module cnt $end
$var wire 1 " CLEAR $end
$var wire 1 # CLK $end
$var reg 3 O Q [2:0] $end
$upscope $end
$scope module dec $end
$var wire 3 P A [2:0] $end
$var wire 1 Q EN $end
$var reg 8 R B [7:0] $end
$upscope $end
$scope module mem $end
$var wire 3 S A [2:0] $end
$var reg 8 T G [7:0] $end
$upscope $end
$scope module mux $end
$var wire 8 U E [7:0] $end
$var wire 3 V Q [2:0] $end
$var wire 1 ! O $end
$upscope $end
$upscope $end
$upscope $end
$enddefinitions $end
#0
$dumpvars
b0 V
b1 U
b1 T
b0 S
b1 R
1Q
b0 P
b0 O
0N
0M
0L
0K
0J
0I
0H
0G
0F
0E
0D
0C
0B
0A
0@
0?
0>
0=
0<
0;
0:
09
08
07
06
05
04
03
12
11
10
0/
b1 .
b1 -
b1 ,
b0 +
b1 *
b1 )
b1 (
b0 '
b0 &
b0 %
b0 $
0#
1"
1!
$end
#500000
0!
b0 )
b0 -
b0 U
02
14
00
b10 *
b10 .
b10 R
b1 '
b1 O
b1 P
b1 V
1#
#1000000
0#
0"
#1500000
18
04
b100 *
b100 .
b100 R
b10 '
b10 O
b10 P
b10 V
1#
#2000000
0#
#2500000
1<
08
b1000 *
b1000 .
b1000 R
b11 '
b11 O
b11 P
b11 V
1#
#3000000
0#
#3500000
1@
0<
b10000 *
b10000 .
b10000 R
b100 '
b100 O
b100 P
b100 V
1#
#4000000
0#
#4500000
1D
0@
b100000 *
b100000 .
b100000 R
b101 '
b101 O
b101 P
b101 V
1#
#5000000
0#
#5500000
1H
0D
b1000000 *
b1000000 .
b1000000 R
b110 '
b110 O
b110 P
b110 V
1#
#6000000
0#
#6500000
1L
0H
b10000000 *
b10000000 .
b10000000 R
b111 '
b111 O
b111 P
b111 V
1#
#7000000
0#
#7500000
1!
b1 )
b1 -
b1 U
12
0L
10
b1 *
b1 .
b1 R
b0 '
b0 O
b0 P
b0 V
1#
#8000000
15
b11 (
b11 ,
b11 T
0#
b1 $
b1 &
b1 S
#8500000
1!
16
b10 )
b10 -
b10 U
02
14
00
b10 *
b10 .
b10 R
b1 '
b1 O
b1 P
b1 V
1#
#9000000
0#
#9500000
b0 )
b0 -
b0 U
06
0!
18
04
b100 *
b100 .
b100 R
b10 '
b10 O
b10 P
b10 V
1#
#10000000
0#
#10500000
1<
08
b1000 *
b1000 .
b1000 R
b11 '
b11 O
b11 P
b11 V
1#
#11000000
0#
#11500000
1@
0<
b10000 *
b10000 .
b10000 R
b100 '
b100 O
b100 P
b100 V
1#
#12000000
0#
#12500000
1D
0@
b100000 *
b100000 .
b100000 R
b101 '
b101 O
b101 P
b101 V
1#
#13000000
0#
#13500000
1H
0D
b1000000 *
b1000000 .
b1000000 R
b110 '
b110 O
b110 P
b110 V
1#
#14000000
0#
#14500000
1L
0H
b10000000 *
b10000000 .
b10000000 R
b111 '
b111 O
b111 P
b111 V
1#
#15000000
0#
#15500000
1!
b1 )
b1 -
b1 U
12
0L
10
b1 *
b1 .
b1 R
b0 '
b0 O
b0 P
b0 V
1#
#16000000
19
b111 (
b111 ,
b111 T
0#
b10 $
b10 &
b10 S
#16500000
1!
16
b10 )
b10 -
b10 U
02
14
00
b10 *
b10 .
b10 R
b1 '
b1 O
b1 P
b1 V
1#
#17000000
0#
#17500000
1:
b100 )
b100 -
b100 U
06
1!
18
04
b100 *
b100 .
b100 R
b10 '
b10 O
b10 P
b10 V
1#
#18000000
0#
#18500000
0!
b0 )
b0 -
b0 U
0:
1<
08
b1000 *
b1000 .
b1000 R
b11 '
b11 O
b11 P
b11 V
1#
#19000000
0#
#19500000
1@
0<
b10000 *
b10000 .
b10000 R
b100 '
b100 O
b100 P
b100 V
1#
#20000000
0#
#20500000
1D
0@
b100000 *
b100000 .
b100000 R
b101 '
b101 O
b101 P
b101 V
1#
#21000000
0#
#21500000
1H
0D
b1000000 *
b1000000 .
b1000000 R
b110 '
b110 O
b110 P
b110 V
1#
#22000000
0#
#22500000
1L
0H
b10000000 *
b10000000 .
b10000000 R
b111 '
b111 O
b111 P
b111 V
1#
#23000000
0#
#23500000
1!
b1 )
b1 -
b1 U
12
0L
10
b1 *
b1 .
b1 R
b0 '
b0 O
b0 P
b0 V
1#
#24000000
1=
b1111 (
b1111 ,
b1111 T
0#
b11 $
b11 &
b11 S
#24500000
1!
16
b10 )
b10 -
b10 U
02
14
00
b10 *
b10 .
b10 R
b1 '
b1 O
b1 P
b1 V
1#
#25000000
0#
#25500000
1:
b100 )
b100 -
b100 U
06
1!
18
04
b100 *
b100 .
b100 R
b10 '
b10 O
b10 P
b10 V
1#
#26000000
0#
#26500000
1!
1>
b1000 )
b1000 -
b1000 U
0:
1<
08
b1000 *
b1000 .
b1000 R
b11 '
b11 O
b11 P
b11 V
1#
#27000000
0#
#27500000
b0 )
b0 -
b0 U
0>
1@
0<
0!
b10000 *
b10000 .
b10000 R
b100 '
b100 O
b100 P
b100 V
1#
#28000000
0#
#28500000
1D
0@
b100000 *
b100000 .
b100000 R
b101 '
b101 O
b101 P
b101 V
1#
#29000000
0#
#29500000
1H
0D
b1000000 *
b1000000 .
b1000000 R
b110 '
b110 O
b110 P
b110 V
1#
#30000000
0#
#30500000
1L
0H
b10000000 *
b10000000 .
b10000000 R
b111 '
b111 O
b111 P
b111 V
1#
#31000000
0#
#31500000
1!
b1 )
b1 -
b1 U
12
0L
10
b1 *
b1 .
b1 R
b0 '
b0 O
b0 P
b0 V
1#
#32000000
1A
b11111 (
b11111 ,
b11111 T
0#
b100 $
b100 &
b100 S
#32500000
1!
16
b10 )
b10 -
b10 U
02
14
00
b10 *
b10 .
b10 R
b1 '
b1 O
b1 P
b1 V
1#
#33000000
0#
#33500000
1:
b100 )
b100 -
b100 U
06
1!
18
04
b100 *
b100 .
b100 R
b10 '
b10 O
b10 P
b10 V
1#
#34000000
0#
#34500000
1!
1>
b1000 )
b1000 -
b1000 U
0:
1<
08
b1000 *
b1000 .
b1000 R
b11 '
b11 O
b11 P
b11 V
1#
#35000000
0#
#35500000
1B
b10000 )
b10000 -
b10000 U
0>
1@
0<
1!
b10000 *
b10000 .
b10000 R
b100 '
b100 O
b100 P
b100 V
1#
#36000000
0#
#36500000
0!
b0 )
b0 -
b0 U
0B
1D
0@
b100000 *
b100000 .
b100000 R
b101 '
b101 O
b101 P
b101 V
1#
#37000000
0#
#37500000
1H
0D
b1000000 *
b1000000 .
b1000000 R
b110 '
b110 O
b110 P
b110 V
1#
#38000000
0#
#38500000
1L
0H
b10000000 *
b10000000 .
b10000000 R
b111 '
b111 O
b111 P
b111 V
1#
#39000000
0#
#39500000
1!
b1 )
b1 -
b1 U
12
0L
10
b1 *
b1 .
b1 R
b0 '
b0 O
b0 P
b0 V
1#
#40000000
1E
b111111 (
b111111 ,
b111111 T
0#
b101 $
b101 &
b101 S
#40500000
1!
16
b10 )
b10 -
b10 U
02
14
00
b10 *
b10 .
b10 R
b1 '
b1 O
b1 P
b1 V
1#
#41000000
0#
#41500000
1:
b100 )
b100 -
b100 U
06
1!
18
04
b100 *
b100 .
b100 R
b10 '
b10 O
b10 P
b10 V
1#
#42000000
0#
#42500000
1!
1>
b1000 )
b1000 -
b1000 U
0:
1<
08
b1000 *
b1000 .
b1000 R
b11 '
b11 O
b11 P
b11 V
1#
#43000000
0#
#43500000
1B
b10000 )
b10000 -
b10000 U
0>
1@
0<
1!
b10000 *
b10000 .
b10000 R
b100 '
b100 O
b100 P
b100 V
1#
#44000000
0#
#44500000
1!
1F
b100000 )
b100000 -
b100000 U
0B
1D
0@
b100000 *
b100000 .
b100000 R
b101 '
b101 O
b101 P
b101 V
1#
#45000000
0#
#45500000
b0 )
b0 -
b0 U
0F
0!
1H
0D
b1000000 *
b1000000 .
b1000000 R
b110 '
b110 O
b110 P
b110 V
1#
#46000000
0#
#46500000
1L
0H
b10000000 *
b10000000 .
b10000000 R
b111 '
b111 O
b111 P
b111 V
1#
#47000000
0#
#47500000
1!
b1 )
b1 -
b1 U
12
0L
10
b1 *
b1 .
b1 R
b0 '
b0 O
b0 P
b0 V
1#
#48000000
1I
b1111111 (
b1111111 ,
b1111111 T
0#
b110 $
b110 &
b110 S
#48500000
1!
16
b10 )
b10 -
b10 U
02
14
00
b10 *
b10 .
b10 R
b1 '
b1 O
b1 P
b1 V
1#
#49000000
0#
#49500000
1:
b100 )
b100 -
b100 U
06
1!
18
04
b100 *
b100 .
b100 R
b10 '
b10 O
b10 P
b10 V
1#
#50000000
0#
#50500000
1!
1>
b1000 )
b1000 -
b1000 U
0:
1<
08
b1000 *
b1000 .
b1000 R
b11 '
b11 O
b11 P
b11 V
1#
#51000000
0#
#51500000
1B
b10000 )
b10000 -
b10000 U
0>
1@
0<
1!
b10000 *
b10000 .
b10000 R
b100 '
b100 O
b100 P
b100 V
1#
#52000000
0#
#52500000
1!
1F
b100000 )
b100000 -
b100000 U
0B
1D
0@
b100000 *
b100000 .
b100000 R
b101 '
b101 O
b101 P
b101 V
1#
#53000000
0#
#53500000
1J
b1000000 )
b1000000 -
b1000000 U
0F
1!
1H
0D
b1000000 *
b1000000 .
b1000000 R
b110 '
b110 O
b110 P
b110 V
1#
#54000000
0#
#54500000
0!
b0 )
b0 -
b0 U
0J
1L
0H
b10000000 *
b10000000 .
b10000000 R
b111 '
b111 O
b111 P
b111 V
1#
#55000000
0#
#55500000
1!
b1 )
b1 -
b1 U
12
0L
10
b1 *
b1 .
b1 R
b0 '
b0 O
b0 P
b0 V
1#
#56000000
1M
b11111111 (
b11111111 ,
b11111111 T
0#
b111 $
b111 &
b111 S
#56500000
1!
16
b10 )
b10 -
b10 U
02
14
00
b10 *
b10 .
b10 R
b1 '
b1 O
b1 P
b1 V
1#
#57000000
0#
#57500000
1:
b100 )
b100 -
b100 U
06
1!
18
04
b100 *
b100 .
b100 R
b10 '
b10 O
b10 P
b10 V
1#
#58000000
0#
#58500000
1!
1>
b1000 )
b1000 -
b1000 U
0:
1<
08
b1000 *
b1000 .
b1000 R
b11 '
b11 O
b11 P
b11 V
1#
#59000000
0#
#59500000
1B
b10000 )
b10000 -
b10000 U
0>
1@
0<
1!
b10000 *
b10000 .
b10000 R
b100 '
b100 O
b100 P
b100 V
1#
#60000000
0#
#60500000
1!
1F
b100000 )
b100000 -
b100000 U
0B
1D
0@
b100000 *
b100000 .
b100000 R
b101 '
b101 O
b101 P
b101 V
1#
#61000000
0#
#61500000
1J
b1000000 )
b1000000 -
b1000000 U
0F
1!
1H
0D
b1000000 *
b1000000 .
b1000000 R
b110 '
b110 O
b110 P
b110 V
1#
#62000000
0#
#62500000
1!
1N
b10000000 )
b10000000 -
b10000000 U
0J
1L
0H
b10000000 *
b10000000 .
b10000000 R
b111 '
b111 O
b111 P
b111 V
1#
#63000000
0#
#63500000
0N
b1 )
b1 -
b1 U
12
0L
10
1!
b1 *
b1 .
b1 R
b0 '
b0 O
b0 P
b0 V
1#
#64000000
0M
0I
0E
0A
0=
09
05
b1 (
b1 ,
b1 T
0#
b0 $
b0 &
b0 S
#64500000
0!
b0 )
b0 -
b0 U
02
14
00
b10 *
b10 .
b10 R
b1 '
b1 O
b1 P
b1 V
1#
#65000000
0#
#65500000
18
04
b100 *
b100 .
b100 R
b10 '
b10 O
b10 P
b10 V
1#
#66000000
0#
#66500000
1<
08
b1000 *
b1000 .
b1000 R
b11 '
b11 O
b11 P
b11 V
1#
#67000000
0#
#67500000
1@
0<
b10000 *
b10000 .
b10000 R
b100 '
b100 O
b100 P
b100 V
1#
#68000000
0#
#68500000
1D
0@
b100000 *
b100000 .
b100000 R
b101 '
b101 O
b101 P
b101 V
1#
#69000000
0#
#69500000
1H
0D
b1000000 *
b1000000 .
b1000000 R
b110 '
b110 O
b110 P
b110 V
1#
#70000000
0#
#70500000
1L
0H
b10000000 *
b10000000 .
b10000000 R
b111 '
b111 O
b111 P
b111 V
1#
#71000000
0#
#71500000
1!
b1 )
b1 -
b1 U
12
0L
10
b1 *
b1 .
b1 R
b0 '
b0 O
b0 P
b0 V
1#
#72000000
15
b11 (
b11 ,
b11 T
0#
b1 $
b1 &
b1 S
#72500000
1!
16
b10 )
b10 -
b10 U
02
14
00
b10 *
b10 .
b10 R
b1 '
b1 O
b1 P
b1 V
1#
#73000000
0#
#73500000
b0 )
b0 -
b0 U
06
0!
18
04
b100 *
b100 .
b100 R
b10 '
b10 O
b10 P
b10 V
1#
#74000000
0#
#74500000
1<
08
b1000 *
b1000 .
b1000 R
b11 '
b11 O
b11 P
b11 V
1#
#75000000
0#
#75500000
1@
0<
b10000 *
b10000 .
b10000 R
b100 '
b100 O
b100 P
b100 V
1#
#76000000
0#
#76500000
1D
0@
b100000 *
b100000 .
b100000 R
b101 '
b101 O
b101 P
b101 V
1#
#77000000
0#
#77500000
1H
0D
b1000000 *
b1000000 .
b1000000 R
b110 '
b110 O
b110 P
b110 V
1#
#78000000
0#
#78500000
1L
0H
b10000000 *
b10000000 .
b10000000 R
b111 '
b111 O
b111 P
b111 V
1#
#79000000
0#
#79500000
1!
b1 )
b1 -
b1 U
12
0L
10
b1 *
b1 .
b1 R
b0 '
b0 O
b0 P
b0 V
1#
#80000000
19
b111 (
b111 ,
b111 T
0#
b10 $
b10 &
b10 S
#80500000
1!
16
b10 )
b10 -
b10 U
02
14
00
b10 *
b10 .
b10 R
b1 '
b1 O
b1 P
b1 V
1#
#81000000
0#
#81500000
1:
b100 )
b100 -
b100 U
06
1!
18
04
b100 *
b100 .
b100 R
b10 '
b10 O
b10 P
b10 V
1#
#82000000
0#
#82500000
0!
b0 )
b0 -
b0 U
0:
1<
08
b1000 *
b1000 .
b1000 R
b11 '
b11 O
b11 P
b11 V
1#
#83000000
0#
#83500000
1@
0<
b10000 *
b10000 .
b10000 R
b100 '
b100 O
b100 P
b100 V
1#
#84000000
0#
#84500000
1D
0@
b100000 *
b100000 .
b100000 R
b101 '
b101 O
b101 P
b101 V
1#
#85000000
0#
#85500000
1H
0D
b1000000 *
b1000000 .
b1000000 R
b110 '
b110 O
b110 P
b110 V
1#
#86000000
0#
#86500000
1L
0H
b10000000 *
b10000000 .
b10000000 R
b111 '
b111 O
b111 P
b111 V
1#
#87000000
0#
#87500000
1!
b1 )
b1 -
b1 U
12
0L
10
b1 *
b1 .
b1 R
b0 '
b0 O
b0 P
b0 V
1#
#88000000
1=
b1111 (
b1111 ,
b1111 T
0#
b11 $
b11 &
b11 S
#88500000
1!
16
b10 )
b10 -
b10 U
02
14
00
b10 *
b10 .
b10 R
b1 '
b1 O
b1 P
b1 V
1#
#89000000
0#
#89500000
1:
b100 )
b100 -
b100 U
06
1!
18
04
b100 *
b100 .
b100 R
b10 '
b10 O
b10 P
b10 V
1#
#90000000
0#
#90500000
1!
1>
b1000 )
b1000 -
b1000 U
0:
1<
08
b1000 *
b1000 .
b1000 R
b11 '
b11 O
b11 P
b11 V
1#
#91000000
0#
#91500000
b0 )
b0 -
b0 U
0>
1@
0<
0!
b10000 *
b10000 .
b10000 R
b100 '
b100 O
b100 P
b100 V
1#
#92000000
0#
#92500000
1D
0@
b100000 *
b100000 .
b100000 R
b101 '
b101 O
b101 P
b101 V
1#
#93000000
0#
#93500000
1H
0D
b1000000 *
b1000000 .
b1000000 R
b110 '
b110 O
b110 P
b110 V
1#
#94000000
0#
#94500000
1L
0H
b10000000 *
b10000000 .
b10000000 R
b111 '
b111 O
b111 P
b111 V
1#
#95000000
0#
#95500000
1!
b1 )
b1 -
b1 U
12
0L
10
b1 *
b1 .
b1 R
b0 '
b0 O
b0 P
b0 V
1#
#96000000
1A
b11111 (
b11111 ,
b11111 T
0#
b100 $
b100 &
b100 S
#96500000
1!
16
b10 )
b10 -
b10 U
02
14
00
b10 *
b10 .
b10 R
b1 '
b1 O
b1 P
b1 V
1#
#97000000
0#
#97500000
1:
b100 )
b100 -
b100 U
06
1!
18
04
b100 *
b100 .
b100 R
b10 '
b10 O
b10 P
b10 V
1#
#98000000
0#
#98500000
1!
1>
b1000 )
b1000 -
b1000 U
0:
1<
08
b1000 *
b1000 .
b1000 R
b11 '
b11 O
b11 P
b11 V
1#
#99000000
0#
#99500000
1B
b10000 )
b10000 -
b10000 U
0>
1@
0<
1!
b10000 *
b10000 .
b10000 R
b100 '
b100 O
b100 P
b100 V
1#
#100000000
0#
#100500000
0!
b0 )
b0 -
b0 U
0B
1D
0@
b100000 *
b100000 .
b100000 R
b101 '
b101 O
b101 P
b101 V
1#
